{
  "contributedRepositories": [
    {
      "codeReviewCount": 0,
      "commitCount": 19,
      "issueCount": 0,
      "nameWithOwner": "haarsh01/harsh_portfolio",
      "ownerAvatarUrl": "https://avatars.githubusercontent.com/u/60865477?u=17a00bac7d641f36fec6599753ac4c510b540888&v=4",
      "ownerLogin": "haarsh01",
      "ownerUrl": "https://github.com/haarsh01",
      "pullRequestCount": 0,
      "total": 19,
      "url": "https://github.com/haarsh01/harsh_portfolio"
    },
    {
      "codeReviewCount": 0,
      "commitCount": 10,
      "issueCount": 0,
      "nameWithOwner": "haarsh01/planify",
      "ownerAvatarUrl": "https://avatars.githubusercontent.com/u/60865477?u=17a00bac7d641f36fec6599753ac4c510b540888&v=4",
      "ownerLogin": "haarsh01",
      "ownerUrl": "https://github.com/haarsh01",
      "pullRequestCount": 0,
      "total": 10,
      "url": "https://github.com/haarsh01/planify"
    },
    {
      "codeReviewCount": 0,
      "commitCount": 6,
      "issueCount": 0,
      "nameWithOwner": "haarsh01/koda",
      "ownerAvatarUrl": "https://avatars.githubusercontent.com/u/60865477?u=17a00bac7d641f36fec6599753ac4c510b540888&v=4",
      "ownerLogin": "haarsh01",
      "ownerUrl": "https://github.com/haarsh01",
      "pullRequestCount": 0,
      "total": 6,
      "url": "https://github.com/haarsh01/koda"
    },
    {
      "codeReviewCount": 0,
      "commitCount": 5,
      "issueCount": 0,
      "nameWithOwner": "haarsh01/genweb",
      "ownerAvatarUrl": "https://avatars.githubusercontent.com/u/60865477?u=17a00bac7d641f36fec6599753ac4c510b540888&v=4",
      "ownerLogin": "haarsh01",
      "ownerUrl": "https://github.com/haarsh01",
      "pullRequestCount": 0,
      "total": 5,
      "url": "https://github.com/haarsh01/genweb"
    },
    {
      "codeReviewCount": 0,
      "commitCount": 3,
      "issueCount": 0,
      "nameWithOwner": "haarsh01/haarsh01",
      "ownerAvatarUrl": "https://avatars.githubusercontent.com/u/60865477?u=17a00bac7d641f36fec6599753ac4c510b540888&v=4",
      "ownerLogin": "haarsh01",
      "ownerUrl": "https://github.com/haarsh01",
      "pullRequestCount": 0,
      "total": 3,
      "url": "https://github.com/haarsh01/haarsh01"
    },
    {
      "codeReviewCount": 0,
      "commitCount": 1,
      "issueCount": 0,
      "nameWithOwner": "haarsh01/AuditLM",
      "ownerAvatarUrl": "https://avatars.githubusercontent.com/u/60865477?u=17a00bac7d641f36fec6599753ac4c510b540888&v=4",
      "ownerLogin": "haarsh01",
      "ownerUrl": "https://github.com/haarsh01",
      "pullRequestCount": 0,
      "total": 1,
      "url": "https://github.com/haarsh01/AuditLM"
    },
    {
      "codeReviewCount": 0,
      "commitCount": 1,
      "issueCount": 0,
      "nameWithOwner": "haarsh01/harshkaushik",
      "ownerAvatarUrl": "https://avatars.githubusercontent.com/u/60865477?u=17a00bac7d641f36fec6599753ac4c510b540888&v=4",
      "ownerLogin": "haarsh01",
      "ownerUrl": "https://github.com/haarsh01",
      "pullRequestCount": 0,
      "total": 1,
      "url": "https://github.com/haarsh01/harshkaushik"
    }
  ],
  "contributions": {
    "months": [
      {
        "firstDay": "2025-07-01",
        "name": "Jul",
        "totalWeeks": 2,
        "year": 2025
      },
      {
        "firstDay": "2025-08-01",
        "name": "Aug",
        "totalWeeks": 5,
        "year": 2025
      },
      {
        "firstDay": "2025-09-01",
        "name": "Sep",
        "totalWeeks": 4,
        "year": 2025
      },
      {
        "firstDay": "2025-10-01",
        "name": "Oct",
        "totalWeeks": 4,
        "year": 2025
      },
      {
        "firstDay": "2025-11-01",
        "name": "Nov",
        "totalWeeks": 5,
        "year": 2025
      },
      {
        "firstDay": "2025-12-01",
        "name": "Dec",
        "totalWeeks": 4,
        "year": 2025
      },
      {
        "firstDay": "2026-01-01",
        "name": "Jan",
        "totalWeeks": 4,
        "year": 2026
      },
      {
        "firstDay": "2026-02-01",
        "name": "Feb",
        "totalWeeks": 4,
        "year": 2026
      },
      {
        "firstDay": "2026-03-01",
        "name": "Mar",
        "totalWeeks": 5,
        "year": 2026
      },
      {
        "firstDay": "2026-04-01",
        "name": "Apr",
        "totalWeeks": 4,
        "year": 2026
      },
      {
        "firstDay": "2026-05-01",
        "name": "May",
        "totalWeeks": 5,
        "year": 2026
      },
      {
        "firstDay": "2026-06-01",
        "name": "Jun",
        "totalWeeks": 4,
        "year": 2026
      },
      {
        "firstDay": "2026-07-01",
        "name": "Jul",
        "totalWeeks": 3,
        "year": 2026
      }
    ],
    "restrictedContributionsCount": 0,
    "totalCommitContributions": 120,
    "totalContributions": 176,
    "totalIssueContributions": 0,
    "totalPullRequestContributions": 49,
    "totalPullRequestReviewContributions": 0,
    "weeks": [
      {
        "days": [
          {
            "count": 0,
            "date": "2025-07-21",
            "level": "NONE",
            "weekday": 1
          },
          {
            "count": 0,
            "date": "2025-07-22",
            "level": "NONE",
            "weekday": 2
          },
          {
            "count": 0,
            "date": "2025-07-23",
            "level": "NONE",
            "weekday": 3
          },
          {
            "count": 0,
            "date": "2025-07-24",
            "level": "NONE",
            "weekday": 4
          },
          {
            "count": 0,
            "date": "2025-07-25",
            "level": "NONE",
            "weekday": 5
          },
          {
            "count": 0,
            "date": "2025-07-26",
            "level": "NONE",
            "weekday": 6
          }
        ],
        "firstDay": "2025-07-21"
      },
      {
        "days": [
          {
            "count": 0,
            "date": "2025-07-27",
            "level": "NONE",
            "weekday": 0
          },
          {
            "count": 0,
            "date": "2025-07-28",
            "level": "NONE",
            "weekday": 1
          },
          {
            "count": 0,
            "date": "2025-07-29",
            "level": "NONE",
            "weekday": 2
          },
          {
            "count": 0,
            "date": "2025-07-30",
            "level": "NONE",
            "weekday": 3
          },
          {
            "count": 0,
            "date": "2025-07-31",
            "level": "NONE",
            "weekday": 4
          },
          {
            "count": 0,
            "date": "2025-08-01",
            "level": "NONE",
            "weekday": 5
          },
          {
            "count": 0,
            "date": "2025-08-02",
            "level": "NONE",
            "weekday": 6
          }
        ],
        "firstDay": "2025-07-27"
      },
      {
        "days": [
          {
            "count": 0,
            "date": "2025-08-03",
            "level": "NONE",
            "weekday": 0
          },
          {
            "count": 0,
            "date": "2025-08-04",
            "level": "NONE",
            "weekday": 1
          },
          {
            "count": 0,
            "date": "2025-08-05",
            "level": "NONE",
            "weekday": 2
          },
          {
            "count": 0,
            "date": "2025-08-06",
            "level": "NONE",
            "weekday": 3
          },
          {
            "count": 0,
            "date": "2025-08-07",
            "level": "NONE",
            "weekday": 4
          },
          {
            "count": 0,
            "date": "2025-08-08",
            "level": "NONE",
            "weekday": 5
          },
          {
            "count": 0,
            "date": "2025-08-09",
            "level": "NONE",
            "weekday": 6
          }
        ],
        "firstDay": "2025-08-03"
      },
      {
        "days": [
          {
            "count": 0,
            "date": "2025-08-10",
            "level": "NONE",
            "weekday": 0
          },
          {
            "count": 0,
            "date": "2025-08-11",
            "level": "NONE",
            "weekday": 1
          },
          {
            "count": 0,
            "date": "2025-08-12",
            "level": "NONE",
            "weekday": 2
          },
          {
            "count": 0,
            "date": "2025-08-13",
            "level": "NONE",
            "weekday": 3
          },
          {
            "count": 0,
            "date": "2025-08-14",
            "level": "NONE",
            "weekday": 4
          },
          {
            "count": 0,
            "date": "2025-08-15",
            "level": "NONE",
            "weekday": 5
          },
          {
            "count": 0,
            "date": "2025-08-16",
            "level": "NONE",
            "weekday": 6
          }
        ],
        "firstDay": "2025-08-10"
      },
      {
        "days": [
          {
            "count": 0,
            "date": "2025-08-17",
            "level": "NONE",
            "weekday": 0
          },
          {
            "count": 0,
            "date": "2025-08-18",
            "level": "NONE",
            "weekday": 1
          },
          {
            "count": 0,
            "date": "2025-08-19",
            "level": "NONE",
            "weekday": 2
          },
          {
            "count": 0,
            "date": "2025-08-20",
            "level": "NONE",
            "weekday": 3
          },
          {
            "count": 0,
            "date": "2025-08-21",
            "level": "NONE",
            "weekday": 4
          },
          {
            "count": 0,
            "date": "2025-08-22",
            "level": "NONE",
            "weekday": 5
          },
          {
            "count": 0,
            "date": "2025-08-23",
            "level": "NONE",
            "weekday": 6
          }
        ],
        "firstDay": "2025-08-17"
      },
      {
        "days": [
          {
            "count": 0,
            "date": "2025-08-24",
            "level": "NONE",
            "weekday": 0
          },
          {
            "count": 0,
            "date": "2025-08-25",
            "level": "NONE",
            "weekday": 1
          },
          {
            "count": 0,
            "date": "2025-08-26",
            "level": "NONE",
            "weekday": 2
          },
          {
            "count": 0,
            "date": "2025-08-27",
            "level": "NONE",
            "weekday": 3
          },
          {
            "count": 0,
            "date": "2025-08-28",
            "level": "NONE",
            "weekday": 4
          },
          {
            "count": 0,
            "date": "2025-08-29",
            "level": "NONE",
            "weekday": 5
          },
          {
            "count": 0,
            "date": "2025-08-30",
            "level": "NONE",
            "weekday": 6
          }
        ],
        "firstDay": "2025-08-24"
      },
      {
        "days": [
          {
            "count": 0,
            "date": "2025-08-31",
            "level": "NONE",
            "weekday": 0
          },
          {
            "count": 0,
            "date": "2025-09-01",
            "level": "NONE",
            "weekday": 1
          },
          {
            "count": 0,
            "date": "2025-09-02",
            "level": "NONE",
            "weekday": 2
          },
          {
            "count": 2,
            "date": "2025-09-03",
            "level": "LOW",
            "weekday": 3
          },
          {
            "count": 0,
            "date": "2025-09-04",
            "level": "NONE",
            "weekday": 4
          },
          {
            "count": 0,
            "date": "2025-09-05",
            "level": "NONE",
            "weekday": 5
          },
          {
            "count": 0,
            "date": "2025-09-06",
            "level": "NONE",
            "weekday": 6
          }
        ],
        "firstDay": "2025-08-31"
      },
      {
        "days": [
          {
            "count": 0,
            "date": "2025-09-07",
            "level": "NONE",
            "weekday": 0
          },
          {
            "count": 0,
            "date": "2025-09-08",
            "level": "NONE",
            "weekday": 1
          },
          {
            "count": 0,
            "date": "2025-09-09",
            "level": "NONE",
            "weekday": 2
          },
          {
            "count": 0,
            "date": "2025-09-10",
            "level": "NONE",
            "weekday": 3
          },
          {
            "count": 0,
            "date": "2025-09-11",
            "level": "NONE",
            "weekday": 4
          },
          {
            "count": 0,
            "date": "2025-09-12",
            "level": "NONE",
            "weekday": 5
          },
          {
            "count": 0,
            "date": "2025-09-13",
            "level": "NONE",
            "weekday": 6
          }
        ],
        "firstDay": "2025-09-07"
      },
      {
        "days": [
          {
            "count": 0,
            "date": "2025-09-14",
            "level": "NONE",
            "weekday": 0
          },
          {
            "count": 0,
            "date": "2025-09-15",
            "level": "NONE",
            "weekday": 1
          },
          {
            "count": 0,
            "date": "2025-09-16",
            "level": "NONE",
            "weekday": 2
          },
          {
            "count": 0,
            "date": "2025-09-17",
            "level": "NONE",
            "weekday": 3
          },
          {
            "count": 3,
            "date": "2025-09-18",
            "level": "LOW",
            "weekday": 4
          },
          {
            "count": 0,
            "date": "2025-09-19",
            "level": "NONE",
            "weekday": 5
          },
          {
            "count": 1,
            "date": "2025-09-20",
            "level": "LOW",
            "weekday": 6
          }
        ],
        "firstDay": "2025-09-14"
      },
      {
        "days": [
          {
            "count": 3,
            "date": "2025-09-21",
            "level": "LOW",
            "weekday": 0
          },
          {
            "count": 3,
            "date": "2025-09-22",
            "level": "LOW",
            "weekday": 1
          },
          {
            "count": 3,
            "date": "2025-09-23",
            "level": "LOW",
            "weekday": 2
          },
          {
            "count": 0,
            "date": "2025-09-24",
            "level": "NONE",
            "weekday": 3
          },
          {
            "count": 0,
            "date": "2025-09-25",
            "level": "NONE",
            "weekday": 4
          },
          {
            "count": 0,
            "date": "2025-09-26",
            "level": "NONE",
            "weekday": 5
          },
          {
            "count": 1,
            "date": "2025-09-27",
            "level": "LOW",
            "weekday": 6
          }
        ],
        "firstDay": "2025-09-21"
      },
      {
        "days": [
          {
            "count": 3,
            "date": "2025-09-28",
            "level": "LOW",
            "weekday": 0
          },
          {
            "count": 0,
            "date": "2025-09-29",
            "level": "NONE",
            "weekday": 1
          },
          {
            "count": 0,
            "date": "2025-09-30",
            "level": "NONE",
            "weekday": 2
          },
          {
            "count": 0,
            "date": "2025-10-01",
            "level": "NONE",
            "weekday": 3
          },
          {
            "count": 0,
            "date": "2025-10-02",
            "level": "NONE",
            "weekday": 4
          },
          {
            "count": 0,
            "date": "2025-10-03",
            "level": "NONE",
            "weekday": 5
          },
          {
            "count": 0,
            "date": "2025-10-04",
            "level": "NONE",
            "weekday": 6
          }
        ],
        "firstDay": "2025-09-28"
      },
      {
        "days": [
          {
            "count": 0,
            "date": "2025-10-05",
            "level": "NONE",
            "weekday": 0
          },
          {
            "count": 0,
            "date": "2025-10-06",
            "level": "NONE",
            "weekday": 1
          },
          {
            "count": 0,
            "date": "2025-10-07",
            "level": "NONE",
            "weekday": 2
          },
          {
            "count": 0,
            "date": "2025-10-08",
            "level": "NONE",
            "weekday": 3
          },
          {
            "count": 0,
            "date": "2025-10-09",
            "level": "NONE",
            "weekday": 4
          },
          {
            "count": 0,
            "date": "2025-10-10",
            "level": "NONE",
            "weekday": 5
          },
          {
            "count": 0,
            "date": "2025-10-11",
            "level": "NONE",
            "weekday": 6
          }
        ],
        "firstDay": "2025-10-05"
      },
      {
        "days": [
          {
            "count": 0,
            "date": "2025-10-12",
            "level": "NONE",
            "weekday": 0
          },
          {
            "count": 0,
            "date": "2025-10-13",
            "level": "NONE",
            "weekday": 1
          },
          {
            "count": 0,
            "date": "2025-10-14",
            "level": "NONE",
            "weekday": 2
          },
          {
            "count": 0,
            "date": "2025-10-15",
            "level": "NONE",
            "weekday": 3
          },
          {
            "count": 0,
            "date": "2025-10-16",
            "level": "NONE",
            "weekday": 4
          },
          {
            "count": 0,
            "date": "2025-10-17",
            "level": "NONE",
            "weekday": 5
          },
          {
            "count": 0,
            "date": "2025-10-18",
            "level": "NONE",
            "weekday": 6
          }
        ],
        "firstDay": "2025-10-12"
      },
      {
        "days": [
          {
            "count": 0,
            "date": "2025-10-19",
            "level": "NONE",
            "weekday": 0
          },
          {
            "count": 0,
            "date": "2025-10-20",
            "level": "NONE",
            "weekday": 1
          },
          {
            "count": 0,
            "date": "2025-10-21",
            "level": "NONE",
            "weekday": 2
          },
          {
            "count": 0,
            "date": "2025-10-22",
            "level": "NONE",
            "weekday": 3
          },
          {
            "count": 0,
            "date": "2025-10-23",
            "level": "NONE",
            "weekday": 4
          },
          {
            "count": 0,
            "date": "2025-10-24",
            "level": "NONE",
            "weekday": 5
          },
          {
            "count": 0,
            "date": "2025-10-25",
            "level": "NONE",
            "weekday": 6
          }
        ],
        "firstDay": "2025-10-19"
      },
      {
        "days": [
          {
            "count": 0,
            "date": "2025-10-26",
            "level": "NONE",
            "weekday": 0
          },
          {
            "count": 0,
            "date": "2025-10-27",
            "level": "NONE",
            "weekday": 1
          },
          {
            "count": 0,
            "date": "2025-10-28",
            "level": "NONE",
            "weekday": 2
          },
          {
            "count": 0,
            "date": "2025-10-29",
            "level": "NONE",
            "weekday": 3
          },
          {
            "count": 0,
            "date": "2025-10-30",
            "level": "NONE",
            "weekday": 4
          },
          {
            "count": 0,
            "date": "2025-10-31",
            "level": "NONE",
            "weekday": 5
          },
          {
            "count": 0,
            "date": "2025-11-01",
            "level": "NONE",
            "weekday": 6
          }
        ],
        "firstDay": "2025-10-26"
      },
      {
        "days": [
          {
            "count": 0,
            "date": "2025-11-02",
            "level": "NONE",
            "weekday": 0
          },
          {
            "count": 0,
            "date": "2025-11-03",
            "level": "NONE",
            "weekday": 1
          },
          {
            "count": 0,
            "date": "2025-11-04",
            "level": "NONE",
            "weekday": 2
          },
          {
            "count": 0,
            "date": "2025-11-05",
            "level": "NONE",
            "weekday": 3
          },
          {
            "count": 0,
            "date": "2025-11-06",
            "level": "NONE",
            "weekday": 4
          },
          {
            "count": 0,
            "date": "2025-11-07",
            "level": "NONE",
            "weekday": 5
          },
          {
            "count": 0,
            "date": "2025-11-08",
            "level": "NONE",
            "weekday": 6
          }
        ],
        "firstDay": "2025-11-02"
      },
      {
        "days": [
          {
            "count": 0,
            "date": "2025-11-09",
            "level": "NONE",
            "weekday": 0
          },
          {
            "count": 0,
            "date": "2025-11-10",
            "level": "NONE",
            "weekday": 1
          },
          {
            "count": 0,
            "date": "2025-11-11",
            "level": "NONE",
            "weekday": 2
          },
          {
            "count": 0,
            "date": "2025-11-12",
            "level": "NONE",
            "weekday": 3
          },
          {
            "count": 0,
            "date": "2025-11-13",
            "level": "NONE",
            "weekday": 4
          },
          {
            "count": 0,
            "date": "2025-11-14",
            "level": "NONE",
            "weekday": 5
          },
          {
            "count": 0,
            "date": "2025-11-15",
            "level": "NONE",
            "weekday": 6
          }
        ],
        "firstDay": "2025-11-09"
      },
      {
        "days": [
          {
            "count": 0,
            "date": "2025-11-16",
            "level": "NONE",
            "weekday": 0
          },
          {
            "count": 0,
            "date": "2025-11-17",
            "level": "NONE",
            "weekday": 1
          },
          {
            "count": 0,
            "date": "2025-11-18",
            "level": "NONE",
            "weekday": 2
          },
          {
            "count": 0,
            "date": "2025-11-19",
            "level": "NONE",
            "weekday": 3
          },
          {
            "count": 0,
            "date": "2025-11-20",
            "level": "NONE",
            "weekday": 4
          },
          {
            "count": 0,
            "date": "2025-11-21",
            "level": "NONE",
            "weekday": 5
          },
          {
            "count": 0,
            "date": "2025-11-22",
            "level": "NONE",
            "weekday": 6
          }
        ],
        "firstDay": "2025-11-16"
      },
      {
        "days": [
          {
            "count": 0,
            "date": "2025-11-23",
            "level": "NONE",
            "weekday": 0
          },
          {
            "count": 0,
            "date": "2025-11-24",
            "level": "NONE",
            "weekday": 1
          },
          {
            "count": 0,
            "date": "2025-11-25",
            "level": "NONE",
            "weekday": 2
          },
          {
            "count": 0,
            "date": "2025-11-26",
            "level": "NONE",
            "weekday": 3
          },
          {
            "count": 0,
            "date": "2025-11-27",
            "level": "NONE",
            "weekday": 4
          },
          {
            "count": 0,
            "date": "2025-11-28",
            "level": "NONE",
            "weekday": 5
          },
          {
            "count": 0,
            "date": "2025-11-29",
            "level": "NONE",
            "weekday": 6
          }
        ],
        "firstDay": "2025-11-23"
      },
      {
        "days": [
          {
            "count": 0,
            "date": "2025-11-30",
            "level": "NONE",
            "weekday": 0
          },
          {
            "count": 0,
            "date": "2025-12-01",
            "level": "NONE",
            "weekday": 1
          },
          {
            "count": 0,
            "date": "2025-12-02",
            "level": "NONE",
            "weekday": 2
          },
          {
            "count": 0,
            "date": "2025-12-03",
            "level": "NONE",
            "weekday": 3
          },
          {
            "count": 0,
            "date": "2025-12-04",
            "level": "NONE",
            "weekday": 4
          },
          {
            "count": 0,
            "date": "2025-12-05",
            "level": "NONE",
            "weekday": 5
          },
          {
            "count": 0,
            "date": "2025-12-06",
            "level": "NONE",
            "weekday": 6
          }
        ],
        "firstDay": "2025-11-30"
      },
      {
        "days": [
          {
            "count": 0,
            "date": "2025-12-07",
            "level": "NONE",
            "weekday": 0
          },
          {
            "count": 0,
            "date": "2025-12-08",
            "level": "NONE",
            "weekday": 1
          },
          {
            "count": 0,
            "date": "2025-12-09",
            "level": "NONE",
            "weekday": 2
          },
          {
            "count": 0,
            "date": "2025-12-10",
            "level": "NONE",
            "weekday": 3
          },
          {
            "count": 0,
            "date": "2025-12-11",
            "level": "NONE",
            "weekday": 4
          },
          {
            "count": 0,
            "date": "2025-12-12",
            "level": "NONE",
            "weekday": 5
          },
          {
            "count": 0,
            "date": "2025-12-13",
            "level": "NONE",
            "weekday": 6
          }
        ],
        "firstDay": "2025-12-07"
      },
      {
        "days": [
          {
            "count": 0,
            "date": "2025-12-14",
            "level": "NONE",
            "weekday": 0
          },
          {
            "count": 0,
            "date": "2025-12-15",
            "level": "NONE",
            "weekday": 1
          },
          {
            "count": 0,
            "date": "2025-12-16",
            "level": "NONE",
            "weekday": 2
          },
          {
            "count": 0,
            "date": "2025-12-17",
            "level": "NONE",
            "weekday": 3
          },
          {
            "count": 0,
            "date": "2025-12-18",
            "level": "NONE",
            "weekday": 4
          },
          {
            "count": 0,
            "date": "2025-12-19",
            "level": "NONE",
            "weekday": 5
          },
          {
            "count": 0,
            "date": "2025-12-20",
            "level": "NONE",
            "weekday": 6
          }
        ],
        "firstDay": "2025-12-14"
      },
      {
        "days": [
          {
            "count": 0,
            "date": "2025-12-21",
            "level": "NONE",
            "weekday": 0
          },
          {
            "count": 0,
            "date": "2025-12-22",
            "level": "NONE",
            "weekday": 1
          },
          {
            "count": 0,
            "date": "2025-12-23",
            "level": "NONE",
            "weekday": 2
          },
          {
            "count": 0,
            "date": "2025-12-24",
            "level": "NONE",
            "weekday": 3
          },
          {
            "count": 0,
            "date": "2025-12-25",
            "level": "NONE",
            "weekday": 4
          },
          {
            "count": 0,
            "date": "2025-12-26",
            "level": "NONE",
            "weekday": 5
          },
          {
            "count": 0,
            "date": "2025-12-27",
            "level": "NONE",
            "weekday": 6
          }
        ],
        "firstDay": "2025-12-21"
      },
      {
        "days": [
          {
            "count": 0,
            "date": "2025-12-28",
            "level": "NONE",
            "weekday": 0
          },
          {
            "count": 0,
            "date": "2025-12-29",
            "level": "NONE",
            "weekday": 1
          },
          {
            "count": 0,
            "date": "2025-12-30",
            "level": "NONE",
            "weekday": 2
          },
          {
            "count": 0,
            "date": "2025-12-31",
            "level": "NONE",
            "weekday": 3
          },
          {
            "count": 0,
            "date": "2026-01-01",
            "level": "NONE",
            "weekday": 4
          },
          {
            "count": 0,
            "date": "2026-01-02",
            "level": "NONE",
            "weekday": 5
          },
          {
            "count": 0,
            "date": "2026-01-03",
            "level": "NONE",
            "weekday": 6
          }
        ],
        "firstDay": "2025-12-28"
      },
      {
        "days": [
          {
            "count": 0,
            "date": "2026-01-04",
            "level": "NONE",
            "weekday": 0
          },
          {
            "count": 0,
            "date": "2026-01-05",
            "level": "NONE",
            "weekday": 1
          },
          {
            "count": 0,
            "date": "2026-01-06",
            "level": "NONE",
            "weekday": 2
          },
          {
            "count": 1,
            "date": "2026-01-07",
            "level": "LOW",
            "weekday": 3
          },
          {
            "count": 2,
            "date": "2026-01-08",
            "level": "LOW",
            "weekday": 4
          },
          {
            "count": 0,
            "date": "2026-01-09",
            "level": "NONE",
            "weekday": 5
          },
          {
            "count": 0,
            "date": "2026-01-10",
            "level": "NONE",
            "weekday": 6
          }
        ],
        "firstDay": "2026-01-04"
      },
      {
        "days": [
          {
            "count": 0,
            "date": "2026-01-11",
            "level": "NONE",
            "weekday": 0
          },
          {
            "count": 2,
            "date": "2026-01-12",
            "level": "LOW",
            "weekday": 1
          },
          {
            "count": 1,
            "date": "2026-01-13",
            "level": "LOW",
            "weekday": 2
          },
          {
            "count": 0,
            "date": "2026-01-14",
            "level": "NONE",
            "weekday": 3
          },
          {
            "count": 2,
            "date": "2026-01-15",
            "level": "LOW",
            "weekday": 4
          },
          {
            "count": 0,
            "date": "2026-01-16",
            "level": "NONE",
            "weekday": 5
          },
          {
            "count": 0,
            "date": "2026-01-17",
            "level": "NONE",
            "weekday": 6
          }
        ],
        "firstDay": "2026-01-11"
      },
      {
        "days": [
          {
            "count": 0,
            "date": "2026-01-18",
            "level": "NONE",
            "weekday": 0
          },
          {
            "count": 2,
            "date": "2026-01-19",
            "level": "LOW",
            "weekday": 1
          },
          {
            "count": 0,
            "date": "2026-01-20",
            "level": "NONE",
            "weekday": 2
          },
          {
            "count": 0,
            "date": "2026-01-21",
            "level": "NONE",
            "weekday": 3
          },
          {
            "count": 0,
            "date": "2026-01-22",
            "level": "NONE",
            "weekday": 4
          },
          {
            "count": 0,
            "date": "2026-01-23",
            "level": "NONE",
            "weekday": 5
          },
          {
            "count": 0,
            "date": "2026-01-24",
            "level": "NONE",
            "weekday": 6
          }
        ],
        "firstDay": "2026-01-18"
      },
      {
        "days": [
          {
            "count": 0,
            "date": "2026-01-25",
            "level": "NONE",
            "weekday": 0
          },
          {
            "count": 5,
            "date": "2026-01-26",
            "level": "MEDIUM",
            "weekday": 1
          },
          {
            "count": 2,
            "date": "2026-01-27",
            "level": "LOW",
            "weekday": 2
          },
          {
            "count": 1,
            "date": "2026-01-28",
            "level": "LOW",
            "weekday": 3
          },
          {
            "count": 2,
            "date": "2026-01-29",
            "level": "LOW",
            "weekday": 4
          },
          {
            "count": 1,
            "date": "2026-01-30",
            "level": "LOW",
            "weekday": 5
          },
          {
            "count": 1,
            "date": "2026-01-31",
            "level": "LOW",
            "weekday": 6
          }
        ],
        "firstDay": "2026-01-25"
      },
      {
        "days": [
          {
            "count": 1,
            "date": "2026-02-01",
            "level": "LOW",
            "weekday": 0
          },
          {
            "count": 0,
            "date": "2026-02-02",
            "level": "NONE",
            "weekday": 1
          },
          {
            "count": 0,
            "date": "2026-02-03",
            "level": "NONE",
            "weekday": 2
          },
          {
            "count": 2,
            "date": "2026-02-04",
            "level": "LOW",
            "weekday": 3
          },
          {
            "count": 1,
            "date": "2026-02-05",
            "level": "LOW",
            "weekday": 4
          },
          {
            "count": 0,
            "date": "2026-02-06",
            "level": "NONE",
            "weekday": 5
          },
          {
            "count": 3,
            "date": "2026-02-07",
            "level": "LOW",
            "weekday": 6
          }
        ],
        "firstDay": "2026-02-01"
      },
      {
        "days": [
          {
            "count": 0,
            "date": "2026-02-08",
            "level": "NONE",
            "weekday": 0
          },
          {
            "count": 0,
            "date": "2026-02-09",
            "level": "NONE",
            "weekday": 1
          },
          {
            "count": 0,
            "date": "2026-02-10",
            "level": "NONE",
            "weekday": 2
          },
          {
            "count": 0,
            "date": "2026-02-11",
            "level": "NONE",
            "weekday": 3
          },
          {
            "count": 0,
            "date": "2026-02-12",
            "level": "NONE",
            "weekday": 4
          },
          {
            "count": 0,
            "date": "2026-02-13",
            "level": "NONE",
            "weekday": 5
          },
          {
            "count": 0,
            "date": "2026-02-14",
            "level": "NONE",
            "weekday": 6
          }
        ],
        "firstDay": "2026-02-08"
      },
      {
        "days": [
          {
            "count": 0,
            "date": "2026-02-15",
            "level": "NONE",
            "weekday": 0
          },
          {
            "count": 0,
            "date": "2026-02-16",
            "level": "NONE",
            "weekday": 1
          },
          {
            "count": 0,
            "date": "2026-02-17",
            "level": "NONE",
            "weekday": 2
          },
          {
            "count": 3,
            "date": "2026-02-18",
            "level": "LOW",
            "weekday": 3
          },
          {
            "count": 2,
            "date": "2026-02-19",
            "level": "LOW",
            "weekday": 4
          },
          {
            "count": 2,
            "date": "2026-02-20",
            "level": "LOW",
            "weekday": 5
          },
          {
            "count": 0,
            "date": "2026-02-21",
            "level": "NONE",
            "weekday": 6
          }
        ],
        "firstDay": "2026-02-15"
      },
      {
        "days": [
          {
            "count": 0,
            "date": "2026-02-22",
            "level": "NONE",
            "weekday": 0
          },
          {
            "count": 0,
            "date": "2026-02-23",
            "level": "NONE",
            "weekday": 1
          },
          {
            "count": 0,
            "date": "2026-02-24",
            "level": "NONE",
            "weekday": 2
          },
          {
            "count": 0,
            "date": "2026-02-25",
            "level": "NONE",
            "weekday": 3
          },
          {
            "count": 0,
            "date": "2026-02-26",
            "level": "NONE",
            "weekday": 4
          },
          {
            "count": 0,
            "date": "2026-02-27",
            "level": "NONE",
            "weekday": 5
          },
          {
            "count": 0,
            "date": "2026-02-28",
            "level": "NONE",
            "weekday": 6
          }
        ],
        "firstDay": "2026-02-22"
      },
      {
        "days": [
          {
            "count": 0,
            "date": "2026-03-01",
            "level": "NONE",
            "weekday": 0
          },
          {
            "count": 0,
            "date": "2026-03-02",
            "level": "NONE",
            "weekday": 1
          },
          {
            "count": 0,
            "date": "2026-03-03",
            "level": "NONE",
            "weekday": 2
          },
          {
            "count": 0,
            "date": "2026-03-04",
            "level": "NONE",
            "weekday": 3
          },
          {
            "count": 2,
            "date": "2026-03-05",
            "level": "LOW",
            "weekday": 4
          },
          {
            "count": 0,
            "date": "2026-03-06",
            "level": "NONE",
            "weekday": 5
          },
          {
            "count": 3,
            "date": "2026-03-07",
            "level": "LOW",
            "weekday": 6
          }
        ],
        "firstDay": "2026-03-01"
      },
      {
        "days": [
          {
            "count": 0,
            "date": "2026-03-08",
            "level": "NONE",
            "weekday": 0
          },
          {
            "count": 8,
            "date": "2026-03-09",
            "level": "HIGH",
            "weekday": 1
          },
          {
            "count": 0,
            "date": "2026-03-10",
            "level": "NONE",
            "weekday": 2
          },
          {
            "count": 0,
            "date": "2026-03-11",
            "level": "NONE",
            "weekday": 3
          },
          {
            "count": 0,
            "date": "2026-03-12",
            "level": "NONE",
            "weekday": 4
          },
          {
            "count": 0,
            "date": "2026-03-13",
            "level": "NONE",
            "weekday": 5
          },
          {
            "count": 0,
            "date": "2026-03-14",
            "level": "NONE",
            "weekday": 6
          }
        ],
        "firstDay": "2026-03-08"
      },
      {
        "days": [
          {
            "count": 2,
            "date": "2026-03-15",
            "level": "LOW",
            "weekday": 0
          },
          {
            "count": 0,
            "date": "2026-03-16",
            "level": "NONE",
            "weekday": 1
          },
          {
            "count": 4,
            "date": "2026-03-17",
            "level": "MEDIUM",
            "weekday": 2
          },
          {
            "count": 0,
            "date": "2026-03-18",
            "level": "NONE",
            "weekday": 3
          },
          {
            "count": 6,
            "date": "2026-03-19",
            "level": "MEDIUM",
            "weekday": 4
          },
          {
            "count": 0,
            "date": "2026-03-20",
            "level": "NONE",
            "weekday": 5
          },
          {
            "count": 4,
            "date": "2026-03-21",
            "level": "MEDIUM",
            "weekday": 6
          }
        ],
        "firstDay": "2026-03-15"
      },
      {
        "days": [
          {
            "count": 2,
            "date": "2026-03-22",
            "level": "LOW",
            "weekday": 0
          },
          {
            "count": 2,
            "date": "2026-03-23",
            "level": "LOW",
            "weekday": 1
          },
          {
            "count": 0,
            "date": "2026-03-24",
            "level": "NONE",
            "weekday": 2
          },
          {
            "count": 2,
            "date": "2026-03-25",
            "level": "LOW",
            "weekday": 3
          },
          {
            "count": 0,
            "date": "2026-03-26",
            "level": "NONE",
            "weekday": 4
          },
          {
            "count": 0,
            "date": "2026-03-27",
            "level": "NONE",
            "weekday": 5
          },
          {
            "count": 0,
            "date": "2026-03-28",
            "level": "NONE",
            "weekday": 6
          }
        ],
        "firstDay": "2026-03-22"
      },
      {
        "days": [
          {
            "count": 12,
            "date": "2026-03-29",
            "level": "VERY_HIGH",
            "weekday": 0
          },
          {
            "count": 1,
            "date": "2026-03-30",
            "level": "LOW",
            "weekday": 1
          },
          {
            "count": 0,
            "date": "2026-03-31",
            "level": "NONE",
            "weekday": 2
          },
          {
            "count": 4,
            "date": "2026-04-01",
            "level": "MEDIUM",
            "weekday": 3
          },
          {
            "count": 12,
            "date": "2026-04-02",
            "level": "VERY_HIGH",
            "weekday": 4
          },
          {
            "count": 0,
            "date": "2026-04-03",
            "level": "NONE",
            "weekday": 5
          },
          {
            "count": 0,
            "date": "2026-04-04",
            "level": "NONE",
            "weekday": 6
          }
        ],
        "firstDay": "2026-03-29"
      },
      {
        "days": [
          {
            "count": 6,
            "date": "2026-04-05",
            "level": "MEDIUM",
            "weekday": 0
          },
          {
            "count": 0,
            "date": "2026-04-06",
            "level": "NONE",
            "weekday": 1
          },
          {
            "count": 0,
            "date": "2026-04-07",
            "level": "NONE",
            "weekday": 2
          },
          {
            "count": 0,
            "date": "2026-04-08",
            "level": "NONE",
            "weekday": 3
          },
          {
            "count": 0,
            "date": "2026-04-09",
            "level": "NONE",
            "weekday": 4
          },
          {
            "count": 0,
            "date": "2026-04-10",
            "level": "NONE",
            "weekday": 5
          },
          {
            "count": 0,
            "date": "2026-04-11",
            "level": "NONE",
            "weekday": 6
          }
        ],
        "firstDay": "2026-04-05"
      },
      {
        "days": [
          {
            "count": 0,
            "date": "2026-04-12",
            "level": "NONE",
            "weekday": 0
          },
          {
            "count": 0,
            "date": "2026-04-13",
            "level": "NONE",
            "weekday": 1
          },
          {
            "count": 0,
            "date": "2026-04-14",
            "level": "NONE",
            "weekday": 2
          },
          {
            "count": 0,
            "date": "2026-04-15",
            "level": "NONE",
            "weekday": 3
          },
          {
            "count": 0,
            "date": "2026-04-16",
            "level": "NONE",
            "weekday": 4
          },
          {
            "count": 0,
            "date": "2026-04-17",
            "level": "NONE",
            "weekday": 5
          },
          {
            "count": 0,
            "date": "2026-04-18",
            "level": "NONE",
            "weekday": 6
          }
        ],
        "firstDay": "2026-04-12"
      },
      {
        "days": [
          {
            "count": 0,
            "date": "2026-04-19",
            "level": "NONE",
            "weekday": 0
          },
          {
            "count": 0,
            "date": "2026-04-20",
            "level": "NONE",
            "weekday": 1
          },
          {
            "count": 0,
            "date": "2026-04-21",
            "level": "NONE",
            "weekday": 2
          },
          {
            "count": 0,
            "date": "2026-04-22",
            "level": "NONE",
            "weekday": 3
          },
          {
            "count": 3,
            "date": "2026-04-23",
            "level": "LOW",
            "weekday": 4
          },
          {
            "count": 0,
            "date": "2026-04-24",
            "level": "NONE",
            "weekday": 5
          },
          {
            "count": 3,
            "date": "2026-04-25",
            "level": "LOW",
            "weekday": 6
          }
        ],
        "firstDay": "2026-04-19"
      },
      {
        "days": [
          {
            "count": 0,
            "date": "2026-04-26",
            "level": "NONE",
            "weekday": 0
          },
          {
            "count": 0,
            "date": "2026-04-27",
            "level": "NONE",
            "weekday": 1
          },
          {
            "count": 3,
            "date": "2026-04-28",
            "level": "LOW",
            "weekday": 2
          },
          {
            "count": 0,
            "date": "2026-04-29",
            "level": "NONE",
            "weekday": 3
          },
          {
            "count": 0,
            "date": "2026-04-30",
            "level": "NONE",
            "weekday": 4
          },
          {
            "count": 0,
            "date": "2026-05-01",
            "level": "NONE",
            "weekday": 5
          },
          {
            "count": 0,
            "date": "2026-05-02",
            "level": "NONE",
            "weekday": 6
          }
        ],
        "firstDay": "2026-04-26"
      },
      {
        "days": [
          {
            "count": 0,
            "date": "2026-05-03",
            "level": "NONE",
            "weekday": 0
          },
          {
            "count": 0,
            "date": "2026-05-04",
            "level": "NONE",
            "weekday": 1
          },
          {
            "count": 0,
            "date": "2026-05-05",
            "level": "NONE",
            "weekday": 2
          },
          {
            "count": 0,
            "date": "2026-05-06",
            "level": "NONE",
            "weekday": 3
          },
          {
            "count": 0,
            "date": "2026-05-07",
            "level": "NONE",
            "weekday": 4
          },
          {
            "count": 0,
            "date": "2026-05-08",
            "level": "NONE",
            "weekday": 5
          },
          {
            "count": 0,
            "date": "2026-05-09",
            "level": "NONE",
            "weekday": 6
          }
        ],
        "firstDay": "2026-05-03"
      },
      {
        "days": [
          {
            "count": 0,
            "date": "2026-05-10",
            "level": "NONE",
            "weekday": 0
          },
          {
            "count": 0,
            "date": "2026-05-11",
            "level": "NONE",
            "weekday": 1
          },
          {
            "count": 0,
            "date": "2026-05-12",
            "level": "NONE",
            "weekday": 2
          },
          {
            "count": 0,
            "date": "2026-05-13",
            "level": "NONE",
            "weekday": 3
          },
          {
            "count": 0,
            "date": "2026-05-14",
            "level": "NONE",
            "weekday": 4
          },
          {
            "count": 0,
            "date": "2026-05-15",
            "level": "NONE",
            "weekday": 5
          },
          {
            "count": 0,
            "date": "2026-05-16",
            "level": "NONE",
            "weekday": 6
          }
        ],
        "firstDay": "2026-05-10"
      },
      {
        "days": [
          {
            "count": 0,
            "date": "2026-05-17",
            "level": "NONE",
            "weekday": 0
          },
          {
            "count": 0,
            "date": "2026-05-18",
            "level": "NONE",
            "weekday": 1
          },
          {
            "count": 0,
            "date": "2026-05-19",
            "level": "NONE",
            "weekday": 2
          },
          {
            "count": 0,
            "date": "2026-05-20",
            "level": "NONE",
            "weekday": 3
          },
          {
            "count": 0,
            "date": "2026-05-21",
            "level": "NONE",
            "weekday": 4
          },
          {
            "count": 0,
            "date": "2026-05-22",
            "level": "NONE",
            "weekday": 5
          },
          {
            "count": 0,
            "date": "2026-05-23",
            "level": "NONE",
            "weekday": 6
          }
        ],
        "firstDay": "2026-05-17"
      },
      {
        "days": [
          {
            "count": 3,
            "date": "2026-05-24",
            "level": "LOW",
            "weekday": 0
          },
          {
            "count": 2,
            "date": "2026-05-25",
            "level": "LOW",
            "weekday": 1
          },
          {
            "count": 0,
            "date": "2026-05-26",
            "level": "NONE",
            "weekday": 2
          },
          {
            "count": 0,
            "date": "2026-05-27",
            "level": "NONE",
            "weekday": 3
          },
          {
            "count": 0,
            "date": "2026-05-28",
            "level": "NONE",
            "weekday": 4
          },
          {
            "count": 0,
            "date": "2026-05-29",
            "level": "NONE",
            "weekday": 5
          },
          {
            "count": 0,
            "date": "2026-05-30",
            "level": "NONE",
            "weekday": 6
          }
        ],
        "firstDay": "2026-05-24"
      },
      {
        "days": [
          {
            "count": 0,
            "date": "2026-05-31",
            "level": "NONE",
            "weekday": 0
          },
          {
            "count": 0,
            "date": "2026-06-01",
            "level": "NONE",
            "weekday": 1
          },
          {
            "count": 0,
            "date": "2026-06-02",
            "level": "NONE",
            "weekday": 2
          },
          {
            "count": 0,
            "date": "2026-06-03",
            "level": "NONE",
            "weekday": 3
          },
          {
            "count": 0,
            "date": "2026-06-04",
            "level": "NONE",
            "weekday": 4
          },
          {
            "count": 0,
            "date": "2026-06-05",
            "level": "NONE",
            "weekday": 5
          },
          {
            "count": 0,
            "date": "2026-06-06",
            "level": "NONE",
            "weekday": 6
          }
        ],
        "firstDay": "2026-05-31"
      },
      {
        "days": [
          {
            "count": 0,
            "date": "2026-06-07",
            "level": "NONE",
            "weekday": 0
          },
          {
            "count": 0,
            "date": "2026-06-08",
            "level": "NONE",
            "weekday": 1
          },
          {
            "count": 2,
            "date": "2026-06-09",
            "level": "LOW",
            "weekday": 2
          },
          {
            "count": 4,
            "date": "2026-06-10",
            "level": "MEDIUM",
            "weekday": 3
          },
          {
            "count": 2,
            "date": "2026-06-11",
            "level": "LOW",
            "weekday": 4
          },
          {
            "count": 0,
            "date": "2026-06-12",
            "level": "NONE",
            "weekday": 5
          },
          {
            "count": 2,
            "date": "2026-06-13",
            "level": "LOW",
            "weekday": 6
          }
        ],
        "firstDay": "2026-06-07"
      },
      {
        "days": [
          {
            "count": 2,
            "date": "2026-06-14",
            "level": "LOW",
            "weekday": 0
          },
          {
            "count": 6,
            "date": "2026-06-15",
            "level": "MEDIUM",
            "weekday": 1
          },
          {
            "count": 0,
            "date": "2026-06-16",
            "level": "NONE",
            "weekday": 2
          },
          {
            "count": 4,
            "date": "2026-06-17",
            "level": "MEDIUM",
            "weekday": 3
          },
          {
            "count": 0,
            "date": "2026-06-18",
            "level": "NONE",
            "weekday": 4
          },
          {
            "count": 0,
            "date": "2026-06-19",
            "level": "NONE",
            "weekday": 5
          },
          {
            "count": 2,
            "date": "2026-06-20",
            "level": "LOW",
            "weekday": 6
          }
        ],
        "firstDay": "2026-06-14"
      },
      {
        "days": [
          {
            "count": 0,
            "date": "2026-06-21",
            "level": "NONE",
            "weekday": 0
          },
          {
            "count": 0,
            "date": "2026-06-22",
            "level": "NONE",
            "weekday": 1
          },
          {
            "count": 0,
            "date": "2026-06-23",
            "level": "NONE",
            "weekday": 2
          },
          {
            "count": 0,
            "date": "2026-06-24",
            "level": "NONE",
            "weekday": 3
          },
          {
            "count": 0,
            "date": "2026-06-25",
            "level": "NONE",
            "weekday": 4
          },
          {
            "count": 0,
            "date": "2026-06-26",
            "level": "NONE",
            "weekday": 5
          },
          {
            "count": 4,
            "date": "2026-06-27",
            "level": "MEDIUM",
            "weekday": 6
          }
        ],
        "firstDay": "2026-06-21"
      },
      {
        "days": [
          {
            "count": 0,
            "date": "2026-06-28",
            "level": "NONE",
            "weekday": 0
          },
          {
            "count": 0,
            "date": "2026-06-29",
            "level": "NONE",
            "weekday": 1
          },
          {
            "count": 2,
            "date": "2026-06-30",
            "level": "LOW",
            "weekday": 2
          },
          {
            "count": 2,
            "date": "2026-07-01",
            "level": "LOW",
            "weekday": 3
          },
          {
            "count": 2,
            "date": "2026-07-02",
            "level": "LOW",
            "weekday": 4
          },
          {
            "count": 0,
            "date": "2026-07-03",
            "level": "NONE",
            "weekday": 5
          },
          {
            "count": 0,
            "date": "2026-07-04",
            "level": "NONE",
            "weekday": 6
          }
        ],
        "firstDay": "2026-06-28"
      },
      {
        "days": [
          {
            "count": 0,
            "date": "2026-07-05",
            "level": "NONE",
            "weekday": 0
          },
          {
            "count": 0,
            "date": "2026-07-06",
            "level": "NONE",
            "weekday": 1
          },
          {
            "count": 2,
            "date": "2026-07-07",
            "level": "LOW",
            "weekday": 2
          },
          {
            "count": 1,
            "date": "2026-07-08",
            "level": "LOW",
            "weekday": 3
          },
          {
            "count": 0,
            "date": "2026-07-09",
            "level": "NONE",
            "weekday": 4
          },
          {
            "count": 0,
            "date": "2026-07-10",
            "level": "NONE",
            "weekday": 5
          },
          {
            "count": 0,
            "date": "2026-07-11",
            "level": "NONE",
            "weekday": 6
          }
        ],
        "firstDay": "2026-07-05"
      },
      {
        "days": [
          {
            "count": 0,
            "date": "2026-07-12",
            "level": "NONE",
            "weekday": 0
          },
          {
            "count": 0,
            "date": "2026-07-13",
            "level": "NONE",
            "weekday": 1
          },
          {
            "count": 0,
            "date": "2026-07-14",
            "level": "NONE",
            "weekday": 2
          },
          {
            "count": 0,
            "date": "2026-07-15",
            "level": "NONE",
            "weekday": 3
          },
          {
            "count": 0,
            "date": "2026-07-16",
            "level": "NONE",
            "weekday": 4
          },
          {
            "count": 0,
            "date": "2026-07-17",
            "level": "NONE",
            "weekday": 5
          },
          {
            "count": 0,
            "date": "2026-07-18",
            "level": "NONE",
            "weekday": 6
          }
        ],
        "firstDay": "2026-07-12"
      },
      {
        "days": [
          {
            "count": 0,
            "date": "2026-07-19",
            "level": "NONE",
            "weekday": 0
          },
          {
            "count": 0,
            "date": "2026-07-20",
            "level": "NONE",
            "weekday": 1
          },
          {
            "count": 0,
            "date": "2026-07-21",
            "level": "NONE",
            "weekday": 2
          }
        ],
        "firstDay": "2026-07-19"
      }
    ]
  },
  "generatedAt": "2026-07-21T20:36:04.497Z",
  "period": {
    "from": "2025-07-21",
    "to": "2026-07-21"
  },
  "profile": {
    "avatarUrl": "https://avatars.githubusercontent.com/u/60865477?u=17a00bac7d641f36fec6599753ac4c510b540888&v=4",
    "bio": null,
    "location": "Halifax, Canada",
    "login": "haarsh01",
    "name": "Harsh Kaushik",
    "profileUrl": "https://github.com/haarsh01"
  },
  "repositories": [
    {
      "createdAt": "2026-01-08T18:50:19Z",
      "defaultBranch": "master",
      "description": null,
      "forksCount": 0,
      "fullName": "haarsh01/harsh_portfolio",
      "homepage": null,
      "htmlUrl": "https://github.com/haarsh01/harsh_portfolio",
      "id": 1130612464,
      "isArchived": false,
      "isFork": false,
      "name": "harsh_portfolio",
      "openIssuesCount": 0,
      "primaryLanguage": "JavaScript",
      "pushedAt": "2026-07-21T18:40:55Z",
      "stargazersCount": 0,
      "topics": [],
      "updatedAt": "2026-07-21T18:42:21Z"
    },
    {
      "createdAt": "2026-07-07T09:31:37Z",
      "defaultBranch": "main",
      "description": null,
      "forksCount": 0,
      "fullName": "haarsh01/AuditLM",
      "homepage": null,
      "htmlUrl": "https://github.com/haarsh01/AuditLM",
      "id": 1292083169,
      "isArchived": false,
      "isFork": false,
      "name": "AuditLM",
      "openIssuesCount": 0,
      "primaryLanguage": null,
      "pushedAt": "2026-07-07T09:31:38Z",
      "stargazersCount": 0,
      "topics": [],
      "updatedAt": "2026-07-07T09:31:55Z"
    },
    {
      "createdAt": "2021-04-15T05:50:28Z",
      "defaultBranch": "main",
      "description": "Harsh Kaushik Portfolio",
      "forksCount": 0,
      "fullName": "haarsh01/haarsh01",
      "homepage": null,
      "htmlUrl": "https://github.com/haarsh01/haarsh01",
      "id": 358142541,
      "isArchived": false,
      "isFork": false,
      "name": "haarsh01",
      "openIssuesCount": 0,
      "primaryLanguage": null,
      "pushedAt": "2026-03-07T22:59:16Z",
      "stargazersCount": 1,
      "topics": [],
      "updatedAt": "2026-03-07T22:59:19Z"
    },
    {
      "createdAt": "2026-02-18T22:27:14Z",
      "defaultBranch": "master",
      "description": null,
      "forksCount": 0,
      "fullName": "haarsh01/koda",
      "homepage": null,
      "htmlUrl": "https://github.com/haarsh01/koda",
      "id": 1161245464,
      "isArchived": false,
      "isFork": false,
      "name": "koda",
      "openIssuesCount": 0,
      "primaryLanguage": "Python",
      "pushedAt": "2026-02-20T14:27:25Z",
      "stargazersCount": 0,
      "topics": [],
      "updatedAt": "2026-02-20T14:27:28Z"
    },
    {
      "createdAt": "2025-09-23T22:53:23Z",
      "defaultBranch": "main",
      "description": null,
      "forksCount": 0,
      "fullName": "haarsh01/genweb",
      "homepage": null,
      "htmlUrl": "https://github.com/haarsh01/genweb",
      "id": 1062910504,
      "isArchived": false,
      "isFork": false,
      "name": "genweb",
      "openIssuesCount": 0,
      "primaryLanguage": "JavaScript",
      "pushedAt": "2025-09-28T09:28:50Z",
      "stargazersCount": 0,
      "topics": [],
      "updatedAt": "2025-09-28T09:28:53Z"
    },
    {
      "createdAt": "2025-09-18T12:33:53Z",
      "defaultBranch": "main",
      "description": null,
      "forksCount": 0,
      "fullName": "haarsh01/planify",
      "homepage": null,
      "htmlUrl": "https://github.com/haarsh01/planify",
      "id": 1059426515,
      "isArchived": false,
      "isFork": false,
      "name": "planify",
      "openIssuesCount": 0,
      "primaryLanguage": "JavaScript",
      "pushedAt": "2025-09-23T18:58:51Z",
      "stargazersCount": 0,
      "topics": [],
      "updatedAt": "2025-09-23T18:58:55Z"
    },
    {
      "createdAt": "2025-09-03T21:45:45Z",
      "defaultBranch": "master",
      "description": null,
      "forksCount": 0,
      "fullName": "haarsh01/harshkaushik",
      "homepage": null,
      "htmlUrl": "https://github.com/haarsh01/harshkaushik",
      "id": 1050047533,
      "isArchived": false,
      "isFork": false,
      "name": "harshkaushik",
      "openIssuesCount": 0,
      "primaryLanguage": "HTML",
      "pushedAt": "2025-09-03T21:45:48Z",
      "stargazersCount": 0,
      "topics": [],
      "updatedAt": "2025-09-03T21:45:53Z"
    },
    {
      "createdAt": "2025-02-16T20:58:14Z",
      "defaultBranch": "master",
      "description": "Github Pages template for personal, portfolio-based websites; forked from mmistakes/minimal-mistakes",
      "forksCount": 0,
      "fullName": "haarsh01/harshkaushik.github.io",
      "homepage": "https://academicpages.github.io",
      "htmlUrl": "https://github.com/haarsh01/harshkaushik.github.io",
      "id": 933858427,
      "isArchived": false,
      "isFork": false,
      "name": "harshkaushik.github.io",
      "openIssuesCount": 0,
      "primaryLanguage": null,
      "pushedAt": "2025-02-15T18:09:58Z",
      "stargazersCount": 0,
      "topics": [],
      "updatedAt": "2025-08-22T01:10:20Z"
    },
    {
      "createdAt": "2025-02-09T18:43:22Z",
      "defaultBranch": "main",
      "description": null,
      "forksCount": 0,
      "fullName": "haarsh01/fin_flow",
      "homepage": null,
      "htmlUrl": "https://github.com/haarsh01/fin_flow",
      "id": 929939937,
      "isArchived": false,
      "isFork": false,
      "name": "fin_flow",
      "openIssuesCount": 0,
      "primaryLanguage": null,
      "pushedAt": "2025-02-09T18:43:23Z",
      "stargazersCount": 0,
      "topics": [],
      "updatedAt": "2025-02-09T18:43:26Z"
    },
    {
      "createdAt": "2025-01-08T15:42:03Z",
      "defaultBranch": "main",
      "description": null,
      "forksCount": 0,
      "fullName": "haarsh01/shelf_space-",
      "homepage": null,
      "htmlUrl": "https://github.com/haarsh01/shelf_space-",
      "id": 913915021,
      "isArchived": false,
      "isFork": false,
      "name": "shelf_space-",
      "openIssuesCount": 0,
      "primaryLanguage": null,
      "pushedAt": "2025-01-08T15:42:03Z",
      "stargazersCount": 0,
      "topics": [],
      "updatedAt": "2025-01-08T15:42:07Z"
    },
    {
      "createdAt": "2024-12-30T22:28:33Z",
      "defaultBranch": "main",
      "description": null,
      "forksCount": 0,
      "fullName": "haarsh01/sample-server",
      "homepage": null,
      "htmlUrl": "https://github.com/haarsh01/sample-server",
      "id": 910289403,
      "isArchived": false,
      "isFork": false,
      "name": "sample-server",
      "openIssuesCount": 0,
      "primaryLanguage": null,
      "pushedAt": "2024-12-30T22:28:33Z",
      "stargazersCount": 0,
      "topics": [],
      "updatedAt": "2024-12-30T22:28:36Z"
    },
    {
      "createdAt": "2024-10-27T19:31:27Z",
      "defaultBranch": "main",
      "description": null,
      "forksCount": 0,
      "fullName": "haarsh01/vascularSurgeryApp",
      "homepage": null,
      "htmlUrl": "https://github.com/haarsh01/vascularSurgeryApp",
      "id": 879393885,
      "isArchived": false,
      "isFork": true,
      "name": "vascularSurgeryApp",
      "openIssuesCount": 0,
      "primaryLanguage": null,
      "pushedAt": "2024-09-14T22:40:22Z",
      "stargazersCount": 0,
      "topics": [],
      "updatedAt": "2024-10-27T19:31:28Z"
    },
    {
      "createdAt": "2024-05-10T16:49:25Z",
      "defaultBranch": "main",
      "description": null,
      "forksCount": 0,
      "fullName": "haarsh01/Applied_Health_Data_Sceince",
      "homepage": null,
      "htmlUrl": "https://github.com/haarsh01/Applied_Health_Data_Sceince",
      "id": 798874427,
      "isArchived": false,
      "isFork": false,
      "name": "Applied_Health_Data_Sceince",
      "openIssuesCount": 0,
      "primaryLanguage": "HTML",
      "pushedAt": "2024-06-17T00:43:32Z",
      "stargazersCount": 0,
      "topics": [],
      "updatedAt": "2024-06-17T00:43:35Z"
    },
    {
      "createdAt": "2023-11-01T18:08:56Z",
      "defaultBranch": "main",
      "description": null,
      "forksCount": 0,
      "fullName": "haarsh01/Harsh-New",
      "homepage": null,
      "htmlUrl": "https://github.com/haarsh01/Harsh-New",
      "id": 713042385,
      "isArchived": false,
      "isFork": false,
      "name": "Harsh-New",
      "openIssuesCount": 0,
      "primaryLanguage": "HTML",
      "pushedAt": "2023-11-01T18:11:15Z",
      "stargazersCount": 0,
      "topics": [],
      "updatedAt": "2023-11-01T18:09:57Z"
    },
    {
      "createdAt": "2022-12-17T12:29:29Z",
      "defaultBranch": "master",
      "description": null,
      "forksCount": 0,
      "fullName": "haarsh01/portfolio",
      "homepage": null,
      "htmlUrl": "https://github.com/haarsh01/portfolio",
      "id": 579357311,
      "isArchived": false,
      "isFork": false,
      "name": "portfolio",
      "openIssuesCount": 0,
      "primaryLanguage": "HTML",
      "pushedAt": "2022-12-17T12:31:35Z",
      "stargazersCount": 0,
      "topics": [],
      "updatedAt": "2022-12-17T12:31:39Z"
    },
    {
      "createdAt": "2022-12-14T13:50:59Z",
      "defaultBranch": "main",
      "description": null,
      "forksCount": 0,
      "fullName": "haarsh01/Personal_Website-",
      "homepage": null,
      "htmlUrl": "https://github.com/haarsh01/Personal_Website-",
      "id": 578201386,
      "isArchived": false,
      "isFork": false,
      "name": "Personal_Website-",
      "openIssuesCount": 0,
      "primaryLanguage": "HTML",
      "pushedAt": "2022-12-14T13:52:45Z",
      "stargazersCount": 0,
      "topics": [],
      "updatedAt": "2022-12-14T13:52:50Z"
    },
    {
      "createdAt": "2021-07-06T17:37:01Z",
      "defaultBranch": "main",
      "description": null,
      "forksCount": 1,
      "fullName": "haarsh01/Harsh-Personal-Website",
      "homepage": null,
      "htmlUrl": "https://github.com/haarsh01/Harsh-Personal-Website",
      "id": 383551287,
      "isArchived": false,
      "isFork": false,
      "name": "Harsh-Personal-Website",
      "openIssuesCount": 0,
      "primaryLanguage": "HTML",
      "pushedAt": "2022-12-14T13:42:23Z",
      "stargazersCount": 0,
      "topics": [],
      "updatedAt": "2022-12-14T13:42:29Z"
    },
    {
      "createdAt": "2022-11-02T10:05:10Z",
      "defaultBranch": "main",
      "description": null,
      "forksCount": 0,
      "fullName": "haarsh01/Whatsapp-Chat_Analyzer",
      "homepage": null,
      "htmlUrl": "https://github.com/haarsh01/Whatsapp-Chat_Analyzer",
      "id": 560806243,
      "isArchived": false,
      "isFork": false,
      "name": "Whatsapp-Chat_Analyzer",
      "openIssuesCount": 0,
      "primaryLanguage": "Python",
      "pushedAt": "2022-11-02T11:14:35Z",
      "stargazersCount": 0,
      "topics": [],
      "updatedAt": "2022-11-02T11:12:27Z"
    },
    {
      "createdAt": "2022-01-18T12:04:50Z",
      "defaultBranch": "main",
      "description": null,
      "forksCount": 0,
      "fullName": "haarsh01/Sari_Ponnet_Website",
      "homepage": null,
      "htmlUrl": "https://github.com/haarsh01/Sari_Ponnet_Website",
      "id": 449268223,
      "isArchived": false,
      "isFork": false,
      "name": "Sari_Ponnet_Website",
      "openIssuesCount": 0,
      "primaryLanguage": "HTML",
      "pushedAt": "2022-03-14T13:14:24Z",
      "stargazersCount": 0,
      "topics": [],
      "updatedAt": "2022-02-11T11:37:18Z"
    },
    {
      "createdAt": "2022-02-03T14:15:03Z",
      "defaultBranch": "main",
      "description": null,
      "forksCount": 0,
      "fullName": "haarsh01/Project-Website",
      "homepage": null,
      "htmlUrl": "https://github.com/haarsh01/Project-Website",
      "id": 455192155,
      "isArchived": false,
      "isFork": false,
      "name": "Project-Website",
      "openIssuesCount": 0,
      "primaryLanguage": "CSS",
      "pushedAt": "2022-02-03T14:18:48Z",
      "stargazersCount": 0,
      "topics": [],
      "updatedAt": "2022-02-03T14:18:51Z"
    },
    {
      "createdAt": "2021-08-23T04:49:33Z",
      "defaultBranch": "main",
      "description": null,
      "forksCount": 4,
      "fullName": "haarsh01/Data-Science-Coding_Ninjas",
      "homepage": null,
      "htmlUrl": "https://github.com/haarsh01/Data-Science-Coding_Ninjas",
      "id": 398976235,
      "isArchived": false,
      "isFork": false,
      "name": "Data-Science-Coding_Ninjas",
      "openIssuesCount": 1,
      "primaryLanguage": "Jupyter Notebook",
      "pushedAt": "2022-01-19T12:54:09Z",
      "stargazersCount": 4,
      "topics": [],
      "updatedAt": "2024-06-19T16:57:07Z"
    },
    {
      "createdAt": "2021-10-25T05:41:47Z",
      "defaultBranch": "main",
      "description": null,
      "forksCount": 0,
      "fullName": "haarsh01/merakilab.github.io",
      "homepage": null,
      "htmlUrl": "https://github.com/haarsh01/merakilab.github.io",
      "id": 420892572,
      "isArchived": false,
      "isFork": true,
      "name": "merakilab.github.io",
      "openIssuesCount": 0,
      "primaryLanguage": "CSS",
      "pushedAt": "2021-10-26T09:51:07Z",
      "stargazersCount": 0,
      "topics": [],
      "updatedAt": "2021-10-26T09:51:10Z"
    },
    {
      "createdAt": "2021-09-10T10:23:19Z",
      "defaultBranch": "main",
      "description": null,
      "forksCount": 0,
      "fullName": "haarsh01/haarsh01.github.io",
      "homepage": " http://www.harshkaushik.me/",
      "htmlUrl": "https://github.com/haarsh01/haarsh01.github.io",
      "id": 405041101,
      "isArchived": false,
      "isFork": false,
      "name": "haarsh01.github.io",
      "openIssuesCount": 0,
      "primaryLanguage": "HTML",
      "pushedAt": "2021-09-10T10:50:32Z",
      "stargazersCount": 0,
      "topics": [],
      "updatedAt": "2021-09-10T23:45:34Z"
    },
    {
      "createdAt": "2021-08-26T17:35:28Z",
      "defaultBranch": "main",
      "description": null,
      "forksCount": 0,
      "fullName": "haarsh01/React-Basic-Projects",
      "homepage": null,
      "htmlUrl": "https://github.com/haarsh01/React-Basic-Projects",
      "id": 400254160,
      "isArchived": false,
      "isFork": false,
      "name": "React-Basic-Projects",
      "openIssuesCount": 0,
      "primaryLanguage": null,
      "pushedAt": "2021-08-26T17:38:30Z",
      "stargazersCount": 0,
      "topics": [],
      "updatedAt": "2021-08-26T17:38:32Z"
    },
    {
      "createdAt": "2021-08-20T10:45:40Z",
      "defaultBranch": "main",
      "description": null,
      "forksCount": 0,
      "fullName": "haarsh01/Payment-Gateway-Integration-Sparks-Foundation",
      "homepage": null,
      "htmlUrl": "https://github.com/haarsh01/Payment-Gateway-Integration-Sparks-Foundation",
      "id": 398243447,
      "isArchived": false,
      "isFork": false,
      "name": "Payment-Gateway-Integration-Sparks-Foundation",
      "openIssuesCount": 0,
      "primaryLanguage": "CSS",
      "pushedAt": "2021-08-20T10:59:12Z",
      "stargazersCount": 0,
      "topics": [],
      "updatedAt": "2021-08-20T10:59:15Z"
    },
    {
      "createdAt": "2021-07-30T12:03:48Z",
      "defaultBranch": "master",
      "description": null,
      "forksCount": 0,
      "fullName": "haarsh01/The-Cybernation-Project---Teach-yourself-cybersecurity",
      "homepage": null,
      "htmlUrl": "https://github.com/haarsh01/The-Cybernation-Project---Teach-yourself-cybersecurity",
      "id": 391049786,
      "isArchived": false,
      "isFork": true,
      "name": "The-Cybernation-Project---Teach-yourself-cybersecurity",
      "openIssuesCount": 0,
      "primaryLanguage": "HTML",
      "pushedAt": "2021-08-15T10:22:23Z",
      "stargazersCount": 0,
      "topics": [],
      "updatedAt": "2021-08-15T10:22:27Z"
    },
    {
      "createdAt": "2021-07-18T00:04:59Z",
      "defaultBranch": "master",
      "description": "Repository to store sample python programs for python learning",
      "forksCount": 0,
      "fullName": "haarsh01/py",
      "homepage": null,
      "htmlUrl": "https://github.com/haarsh01/py",
      "id": 387058048,
      "isArchived": false,
      "isFork": true,
      "name": "py",
      "openIssuesCount": 0,
      "primaryLanguage": null,
      "pushedAt": "2021-07-14T09:57:15Z",
      "stargazersCount": 0,
      "topics": [],
      "updatedAt": "2021-07-18T00:05:00Z"
    },
    {
      "createdAt": "2021-07-04T17:25:45Z",
      "defaultBranch": "main",
      "description": null,
      "forksCount": 0,
      "fullName": "haarsh01/Keeper-App-React",
      "homepage": null,
      "htmlUrl": "https://github.com/haarsh01/Keeper-App-React",
      "id": 382910088,
      "isArchived": false,
      "isFork": false,
      "name": "Keeper-App-React",
      "openIssuesCount": 0,
      "primaryLanguage": null,
      "pushedAt": "2021-07-04T17:25:45Z",
      "stargazersCount": 0,
      "topics": [],
      "updatedAt": "2021-07-04T17:25:48Z"
    },
    {
      "createdAt": "2021-03-08T15:14:56Z",
      "defaultBranch": "main",
      "description": null,
      "forksCount": 0,
      "fullName": "haarsh01/Leet-Code-Solutions",
      "homepage": null,
      "htmlUrl": "https://github.com/haarsh01/Leet-Code-Solutions",
      "id": 345698247,
      "isArchived": false,
      "isFork": false,
      "name": "Leet-Code-Solutions",
      "openIssuesCount": 0,
      "primaryLanguage": "C++",
      "pushedAt": "2021-07-03T17:26:52Z",
      "stargazersCount": 0,
      "topics": [],
      "updatedAt": "2021-07-03T17:26:55Z"
    },
    {
      "createdAt": "2021-06-23T11:38:57Z",
      "defaultBranch": "main",
      "description": null,
      "forksCount": 0,
      "fullName": "haarsh01/Modal-Window-JS",
      "homepage": null,
      "htmlUrl": "https://github.com/haarsh01/Modal-Window-JS",
      "id": 379582431,
      "isArchived": false,
      "isFork": false,
      "name": "Modal-Window-JS",
      "openIssuesCount": 0,
      "primaryLanguage": "CSS",
      "pushedAt": "2021-06-23T12:30:08Z",
      "stargazersCount": 0,
      "topics": [],
      "updatedAt": "2021-06-23T12:30:11Z"
    },
    {
      "createdAt": "2021-06-17T11:16:19Z",
      "defaultBranch": "main",
      "description": null,
      "forksCount": 0,
      "fullName": "haarsh01/Guess-My-Number",
      "homepage": null,
      "htmlUrl": "https://github.com/haarsh01/Guess-My-Number",
      "id": 377803914,
      "isArchived": false,
      "isFork": false,
      "name": "Guess-My-Number",
      "openIssuesCount": 0,
      "primaryLanguage": "JavaScript",
      "pushedAt": "2021-06-17T11:18:59Z",
      "stargazersCount": 0,
      "topics": [],
      "updatedAt": "2021-06-17T11:19:02Z"
    },
    {
      "createdAt": "2021-01-22T18:29:10Z",
      "defaultBranch": "main",
      "description": "It is a Glass Morphism Calculator using Html , CSS and JavaScript .",
      "forksCount": 0,
      "fullName": "haarsh01/Glass-Morphism-Calculator",
      "homepage": null,
      "htmlUrl": "https://github.com/haarsh01/Glass-Morphism-Calculator",
      "id": 332030361,
      "isArchived": false,
      "isFork": false,
      "name": "Glass-Morphism-Calculator",
      "openIssuesCount": 0,
      "primaryLanguage": "CSS",
      "pushedAt": "2021-06-11T13:20:03Z",
      "stargazersCount": 1,
      "topics": [],
      "updatedAt": "2021-06-11T13:20:06Z"
    },
    {
      "createdAt": "2021-06-08T15:38:54Z",
      "defaultBranch": "main",
      "description": null,
      "forksCount": 0,
      "fullName": "haarsh01/pig-game-JS",
      "homepage": null,
      "htmlUrl": "https://github.com/haarsh01/pig-game-JS",
      "id": 375061578,
      "isArchived": false,
      "isFork": false,
      "name": "pig-game-JS",
      "openIssuesCount": 0,
      "primaryLanguage": "JavaScript",
      "pushedAt": "2021-06-11T13:15:51Z",
      "stargazersCount": 0,
      "topics": [],
      "updatedAt": "2021-06-11T13:15:53Z"
    },
    {
      "createdAt": "2021-03-02T15:55:00Z",
      "defaultBranch": "main",
      "description": null,
      "forksCount": 0,
      "fullName": "haarsh01/Hackerrank-Problem-Solving",
      "homepage": null,
      "htmlUrl": "https://github.com/haarsh01/Hackerrank-Problem-Solving",
      "id": 343828802,
      "isArchived": false,
      "isFork": false,
      "name": "Hackerrank-Problem-Solving",
      "openIssuesCount": 0,
      "primaryLanguage": "C++",
      "pushedAt": "2021-06-02T17:16:10Z",
      "stargazersCount": 0,
      "topics": [],
      "updatedAt": "2021-06-02T17:16:13Z"
    },
    {
      "createdAt": "2021-05-24T05:15:42Z",
      "defaultBranch": "main",
      "description": null,
      "forksCount": 0,
      "fullName": "haarsh01/Login-form-CSS",
      "homepage": null,
      "htmlUrl": "https://github.com/haarsh01/Login-form-CSS",
      "id": 370235508,
      "isArchived": false,
      "isFork": false,
      "name": "Login-form-CSS",
      "openIssuesCount": 0,
      "primaryLanguage": "CSS",
      "pushedAt": "2021-05-24T05:27:02Z",
      "stargazersCount": 0,
      "topics": [],
      "updatedAt": "2021-05-24T05:27:03Z"
    },
    {
      "createdAt": "2021-10-24T14:59:45Z",
      "defaultBranch": "master",
      "description": null,
      "forksCount": 0,
      "fullName": "haarsh01/meraki-website",
      "homepage": null,
      "htmlUrl": "https://github.com/haarsh01/meraki-website",
      "id": 420714962,
      "isArchived": false,
      "isFork": true,
      "name": "meraki-website",
      "openIssuesCount": 0,
      "primaryLanguage": null,
      "pushedAt": "2021-05-19T08:15:53Z",
      "stargazersCount": 0,
      "topics": [],
      "updatedAt": "2023-06-14T15:37:59Z"
    },
    {
      "createdAt": "2021-05-12T18:55:57Z",
      "defaultBranch": "main",
      "description": "Join the GitHub Graduation Yearbook and \"walk the stage\" on June 5.",
      "forksCount": 0,
      "fullName": "haarsh01/GitHubGraduation-2021",
      "homepage": null,
      "htmlUrl": "https://github.com/haarsh01/GitHubGraduation-2021",
      "id": 366822904,
      "isArchived": false,
      "isFork": true,
      "name": "GitHubGraduation-2021",
      "openIssuesCount": 0,
      "primaryLanguage": "JavaScript",
      "pushedAt": "2021-05-12T19:25:43Z",
      "stargazersCount": 0,
      "topics": [],
      "updatedAt": "2021-05-12T19:25:47Z"
    },
    {
      "createdAt": "2021-05-16T04:47:41Z",
      "defaultBranch": "main",
      "description": "IPU Results Portal, the best getaway to obtain results 🔥🔥",
      "forksCount": 0,
      "fullName": "haarsh01/IPU-Website",
      "homepage": "https://ipuresultskg.herokuapp.com",
      "htmlUrl": "https://github.com/haarsh01/IPU-Website",
      "id": 367786990,
      "isArchived": false,
      "isFork": true,
      "name": "IPU-Website",
      "openIssuesCount": 0,
      "primaryLanguage": null,
      "pushedAt": "2021-04-29T11:57:36Z",
      "stargazersCount": 0,
      "topics": [],
      "updatedAt": "2021-05-16T04:47:42Z"
    },
    {
      "createdAt": "2021-04-16T23:08:15Z",
      "defaultBranch": "main",
      "description": null,
      "forksCount": 0,
      "fullName": "haarsh01/30-Days-Code-HackerRank",
      "homepage": null,
      "htmlUrl": "https://github.com/haarsh01/30-Days-Code-HackerRank",
      "id": 358739388,
      "isArchived": false,
      "isFork": false,
      "name": "30-Days-Code-HackerRank",
      "openIssuesCount": 0,
      "primaryLanguage": "C++",
      "pushedAt": "2021-04-26T17:13:52Z",
      "stargazersCount": 0,
      "topics": [],
      "updatedAt": "2021-04-26T17:13:54Z"
    },
    {
      "createdAt": "2021-04-21T02:47:52Z",
      "defaultBranch": "main",
      "description": null,
      "forksCount": 0,
      "fullName": "haarsh01/10-Days-Javascript",
      "homepage": null,
      "htmlUrl": "https://github.com/haarsh01/10-Days-Javascript",
      "id": 360013021,
      "isArchived": false,
      "isFork": false,
      "name": "10-Days-Javascript",
      "openIssuesCount": 0,
      "primaryLanguage": null,
      "pushedAt": "2021-04-21T02:47:53Z",
      "stargazersCount": 0,
      "topics": [],
      "updatedAt": "2021-04-21T02:47:52Z"
    },
    {
      "createdAt": "2021-02-25T17:36:34Z",
      "defaultBranch": "main",
      "description": null,
      "forksCount": 0,
      "fullName": "haarsh01/Weather-App-Javascript",
      "homepage": null,
      "htmlUrl": "https://github.com/haarsh01/Weather-App-Javascript",
      "id": 342326863,
      "isArchived": false,
      "isFork": false,
      "name": "Weather-App-Javascript",
      "openIssuesCount": 0,
      "primaryLanguage": "CSS",
      "pushedAt": "2021-04-20T10:09:25Z",
      "stargazersCount": 0,
      "topics": [],
      "updatedAt": "2021-04-20T10:09:28Z"
    },
    {
      "createdAt": "2021-03-27T19:59:48Z",
      "defaultBranch": "master",
      "description": "Scripts that will make you go WOW 😍💻",
      "forksCount": 0,
      "fullName": "haarsh01/Rotten-Scripts",
      "homepage": null,
      "htmlUrl": "https://github.com/haarsh01/Rotten-Scripts",
      "id": 352165208,
      "isArchived": false,
      "isFork": true,
      "name": "Rotten-Scripts",
      "openIssuesCount": 0,
      "primaryLanguage": "Python",
      "pushedAt": "2021-04-19T12:25:03Z",
      "stargazersCount": 0,
      "topics": [],
      "updatedAt": "2021-04-19T12:25:06Z"
    },
    {
      "createdAt": "2021-04-14T11:07:26Z",
      "defaultBranch": "main",
      "description": "A collection of CSS Arts.",
      "forksCount": 0,
      "fullName": "haarsh01/css-art-gallery",
      "homepage": "https://css-art-gallery.netlify.app/",
      "htmlUrl": "https://github.com/haarsh01/css-art-gallery",
      "id": 357874676,
      "isArchived": false,
      "isFork": true,
      "name": "css-art-gallery",
      "openIssuesCount": 0,
      "primaryLanguage": "JavaScript",
      "pushedAt": "2021-04-14T11:52:17Z",
      "stargazersCount": 0,
      "topics": [],
      "updatedAt": "2021-04-14T11:52:20Z"
    },
    {
      "createdAt": "2021-01-25T17:11:33Z",
      "defaultBranch": "main",
      "description": null,
      "forksCount": 0,
      "fullName": "haarsh01/Recursion_solutions",
      "homepage": null,
      "htmlUrl": "https://github.com/haarsh01/Recursion_solutions",
      "id": 332822615,
      "isArchived": false,
      "isFork": false,
      "name": "Recursion_solutions",
      "openIssuesCount": 0,
      "primaryLanguage": "C++",
      "pushedAt": "2021-04-11T17:06:59Z",
      "stargazersCount": 0,
      "topics": [],
      "updatedAt": "2021-04-11T17:07:00Z"
    },
    {
      "createdAt": "2021-04-10T16:25:45Z",
      "defaultBranch": "main",
      "description": null,
      "forksCount": 0,
      "fullName": "haarsh01/MIDAS-Web-App-Task",
      "homepage": null,
      "htmlUrl": "https://github.com/haarsh01/MIDAS-Web-App-Task",
      "id": 356636306,
      "isArchived": false,
      "isFork": false,
      "name": "MIDAS-Web-App-Task",
      "openIssuesCount": 0,
      "primaryLanguage": "CSS",
      "pushedAt": "2021-04-10T16:28:14Z",
      "stargazersCount": 0,
      "topics": [],
      "updatedAt": "2021-04-10T16:28:15Z"
    },
    {
      "createdAt": "2021-04-20T10:24:20Z",
      "defaultBranch": "master",
      "description": "Starter files, final projects and FAQ for my Complete JavaScript course",
      "forksCount": 0,
      "fullName": "haarsh01/complete-javascript-course",
      "homepage": "https://www.udemy.com/the-complete-javascript-course/?couponCode=C3GITHUB10",
      "htmlUrl": "https://github.com/haarsh01/complete-javascript-course",
      "id": 359773783,
      "isArchived": false,
      "isFork": true,
      "name": "complete-javascript-course",
      "openIssuesCount": 0,
      "primaryLanguage": null,
      "pushedAt": "2021-03-30T20:40:00Z",
      "stargazersCount": 0,
      "topics": [],
      "updatedAt": "2021-04-20T10:24:22Z"
    },
    {
      "createdAt": "2021-02-10T04:58:47Z",
      "defaultBranch": "main",
      "description": null,
      "forksCount": 0,
      "fullName": "haarsh01/100-Days-of-Python-Code",
      "homepage": null,
      "htmlUrl": "https://github.com/haarsh01/100-Days-of-Python-Code",
      "id": 337621692,
      "isArchived": false,
      "isFork": false,
      "name": "100-Days-of-Python-Code",
      "openIssuesCount": 0,
      "primaryLanguage": "Python",
      "pushedAt": "2021-03-21T14:25:07Z",
      "stargazersCount": 0,
      "topics": [],
      "updatedAt": "2021-03-21T14:25:09Z"
    },
    {
      "createdAt": "2021-03-15T14:09:06Z",
      "defaultBranch": "master",
      "description": "A student's savior to submit those assignments by just typing them out and getting it handwritten on the go!",
      "forksCount": 0,
      "fullName": "haarsh01/doc2pen",
      "homepage": "https://doc2pen.netlify.app/",
      "htmlUrl": "https://github.com/haarsh01/doc2pen",
      "id": 347994800,
      "isArchived": false,
      "isFork": true,
      "name": "doc2pen",
      "openIssuesCount": 0,
      "primaryLanguage": null,
      "pushedAt": "2021-03-15T13:40:21Z",
      "stargazersCount": 0,
      "topics": [],
      "updatedAt": "2021-03-15T14:09:07Z"
    },
    {
      "createdAt": "2021-01-30T16:32:37Z",
      "defaultBranch": "main",
      "description": null,
      "forksCount": 0,
      "fullName": "haarsh01/cpp_solutions",
      "homepage": null,
      "htmlUrl": "https://github.com/haarsh01/cpp_solutions",
      "id": 334459409,
      "isArchived": false,
      "isFork": false,
      "name": "cpp_solutions",
      "openIssuesCount": 0,
      "primaryLanguage": "C++",
      "pushedAt": "2021-02-28T13:18:26Z",
      "stargazersCount": 0,
      "topics": [],
      "updatedAt": "2021-02-28T13:18:28Z"
    },
    {
      "createdAt": "2021-02-20T10:44:32Z",
      "defaultBranch": "main",
      "description": null,
      "forksCount": 0,
      "fullName": "haarsh01/telegram-bot",
      "homepage": null,
      "htmlUrl": "https://github.com/haarsh01/telegram-bot",
      "id": 340629509,
      "isArchived": false,
      "isFork": false,
      "name": "telegram-bot",
      "openIssuesCount": 0,
      "primaryLanguage": "Python",
      "pushedAt": "2021-02-20T10:45:24Z",
      "stargazersCount": 0,
      "topics": [],
      "updatedAt": "2021-02-20T10:45:26Z"
    },
    {
      "createdAt": "2021-02-11T11:06:44Z",
      "defaultBranch": "main",
      "description": null,
      "forksCount": 0,
      "fullName": "haarsh01/Movie-Recommendation-System",
      "homepage": null,
      "htmlUrl": "https://github.com/haarsh01/Movie-Recommendation-System",
      "id": 338004859,
      "isArchived": false,
      "isFork": false,
      "name": "Movie-Recommendation-System",
      "openIssuesCount": 0,
      "primaryLanguage": "Jupyter Notebook",
      "pushedAt": "2021-02-11T11:09:16Z",
      "stargazersCount": 0,
      "topics": [],
      "updatedAt": "2021-02-11T11:09:19Z"
    },
    {
      "createdAt": "2021-02-08T07:32:58Z",
      "defaultBranch": "main",
      "description": "Hist Painting Project using colorgram library in python language .",
      "forksCount": 0,
      "fullName": "haarsh01/Hist-Painting-Project-Python",
      "homepage": null,
      "htmlUrl": "https://github.com/haarsh01/Hist-Painting-Project-Python",
      "id": 336994410,
      "isArchived": false,
      "isFork": false,
      "name": "Hist-Painting-Project-Python",
      "openIssuesCount": 0,
      "primaryLanguage": "Python",
      "pushedAt": "2021-02-08T07:33:26Z",
      "stargazersCount": 0,
      "topics": [],
      "updatedAt": "2021-02-08T07:33:28Z"
    },
    {
      "createdAt": "2021-02-07T05:38:32Z",
      "defaultBranch": "main",
      "description": "It is a project of OpenCV face recognition using Python language .",
      "forksCount": 0,
      "fullName": "haarsh01/face_recognition-using-python",
      "homepage": null,
      "htmlUrl": "https://github.com/haarsh01/face_recognition-using-python",
      "id": 336710055,
      "isArchived": false,
      "isFork": false,
      "name": "face_recognition-using-python",
      "openIssuesCount": 0,
      "primaryLanguage": "Python",
      "pushedAt": "2021-02-07T05:39:07Z",
      "stargazersCount": 0,
      "topics": [],
      "updatedAt": "2021-02-07T05:39:09Z"
    },
    {
      "createdAt": "2021-02-03T10:34:16Z",
      "defaultBranch": "main",
      "description": null,
      "forksCount": 0,
      "fullName": "haarsh01/openCV-practice",
      "homepage": null,
      "htmlUrl": "https://github.com/haarsh01/openCV-practice",
      "id": 335588813,
      "isArchived": false,
      "isFork": false,
      "name": "openCV-practice",
      "openIssuesCount": 0,
      "primaryLanguage": "Python",
      "pushedAt": "2021-02-03T10:35:13Z",
      "stargazersCount": 0,
      "topics": [],
      "updatedAt": "2021-02-03T10:35:15Z"
    },
    {
      "createdAt": "2021-01-27T04:08:02Z",
      "defaultBranch": "main",
      "description": null,
      "forksCount": 0,
      "fullName": "haarsh01/Turtle-graphics-Python-Documentation",
      "homepage": null,
      "htmlUrl": "https://github.com/haarsh01/Turtle-graphics-Python-Documentation",
      "id": 333299245,
      "isArchived": false,
      "isFork": false,
      "name": "Turtle-graphics-Python-Documentation",
      "openIssuesCount": 0,
      "primaryLanguage": null,
      "pushedAt": "2021-01-27T04:08:52Z",
      "stargazersCount": 0,
      "topics": [],
      "updatedAt": "2021-01-27T04:08:54Z"
    },
    {
      "createdAt": "2021-01-26T12:55:20Z",
      "defaultBranch": "main",
      "description": null,
      "forksCount": 0,
      "fullName": "haarsh01/python-spirograph",
      "homepage": null,
      "htmlUrl": "https://github.com/haarsh01/python-spirograph",
      "id": 333084889,
      "isArchived": false,
      "isFork": false,
      "name": "python-spirograph",
      "openIssuesCount": 0,
      "primaryLanguage": "Python",
      "pushedAt": "2021-01-26T12:55:51Z",
      "stargazersCount": 0,
      "topics": [],
      "updatedAt": "2021-01-26T12:55:53Z"
    },
    {
      "createdAt": "2021-01-18T17:09:43Z",
      "defaultBranch": "main",
      "description": "I have created a clock with hour, minute and second hand using Pure HTML CSS and JS.",
      "forksCount": 0,
      "fullName": "haarsh01/Clock-Javascript-",
      "homepage": null,
      "htmlUrl": "https://github.com/haarsh01/Clock-Javascript-",
      "id": 330734926,
      "isArchived": false,
      "isFork": false,
      "name": "Clock-Javascript-",
      "openIssuesCount": 0,
      "primaryLanguage": "CSS",
      "pushedAt": "2021-01-18T17:10:22Z",
      "stargazersCount": 0,
      "topics": [],
      "updatedAt": "2021-01-18T17:10:24Z"
    },
    {
      "createdAt": "2021-11-19T18:52:13Z",
      "defaultBranch": "main",
      "description": null,
      "forksCount": 0,
      "fullName": "haarsh01/Zoltar-The-fortune-telling-AI",
      "homepage": null,
      "htmlUrl": "https://github.com/haarsh01/Zoltar-The-fortune-telling-AI",
      "id": 429903243,
      "isArchived": false,
      "isFork": true,
      "name": "Zoltar-The-fortune-telling-AI",
      "openIssuesCount": 0,
      "primaryLanguage": null,
      "pushedAt": "2020-10-24T15:55:30Z",
      "stargazersCount": 0,
      "topics": [],
      "updatedAt": "2021-11-19T18:52:14Z"
    },
    {
      "createdAt": "2020-10-21T18:50:17Z",
      "defaultBranch": "main",
      "description": null,
      "forksCount": 0,
      "fullName": "haarsh01/The-Simon-Game-",
      "homepage": null,
      "htmlUrl": "https://github.com/haarsh01/The-Simon-Game-",
      "id": 306118525,
      "isArchived": false,
      "isFork": false,
      "name": "The-Simon-Game-",
      "openIssuesCount": 0,
      "primaryLanguage": "JavaScript",
      "pushedAt": "2020-10-21T18:52:08Z",
      "stargazersCount": 0,
      "topics": [],
      "updatedAt": "2020-10-21T18:52:09Z"
    },
    {
      "createdAt": "2020-10-20T20:01:58Z",
      "defaultBranch": "main",
      "description": null,
      "forksCount": 0,
      "fullName": "haarsh01/Drums-Kit-",
      "homepage": null,
      "htmlUrl": "https://github.com/haarsh01/Drums-Kit-",
      "id": 305820170,
      "isArchived": false,
      "isFork": false,
      "name": "Drums-Kit-",
      "openIssuesCount": 0,
      "primaryLanguage": "JavaScript",
      "pushedAt": "2020-10-21T03:45:40Z",
      "stargazersCount": 0,
      "topics": [],
      "updatedAt": "2020-10-21T03:45:41Z"
    },
    {
      "createdAt": "2021-05-26T10:21:23Z",
      "defaultBranch": "master",
      "description": "Learn to Code While Building Apps - The Complete Flutter Development Bootcamp",
      "forksCount": 0,
      "fullName": "haarsh01/Flutter-Course-Resources",
      "homepage": "https://www.appbrewery.co",
      "htmlUrl": "https://github.com/haarsh01/Flutter-Course-Resources",
      "id": 370992326,
      "isArchived": false,
      "isFork": true,
      "name": "Flutter-Course-Resources",
      "openIssuesCount": 0,
      "primaryLanguage": null,
      "pushedAt": "2020-10-06T22:37:30Z",
      "stargazersCount": 0,
      "topics": [],
      "updatedAt": "2021-05-26T10:21:25Z"
    },
    {
      "createdAt": "2020-08-16T12:18:41Z",
      "defaultBranch": "master",
      "description": null,
      "forksCount": 0,
      "fullName": "haarsh01/My-Personal-Site",
      "homepage": null,
      "htmlUrl": "https://github.com/haarsh01/My-Personal-Site",
      "id": 287937890,
      "isArchived": false,
      "isFork": false,
      "name": "My-Personal-Site",
      "openIssuesCount": 0,
      "primaryLanguage": "HTML",
      "pushedAt": "2020-08-16T12:21:12Z",
      "stargazersCount": 0,
      "topics": [],
      "updatedAt": "2020-08-16T12:21:14Z"
    },
    {
      "createdAt": "2021-11-19T18:53:10Z",
      "defaultBranch": "master",
      "description": "Project made in the DSCBVP MANIFESTE",
      "forksCount": 0,
      "fullName": "haarsh01/JESSIE",
      "homepage": null,
      "htmlUrl": "https://github.com/haarsh01/JESSIE",
      "id": 429903460,
      "isArchived": false,
      "isFork": true,
      "name": "JESSIE",
      "openIssuesCount": 0,
      "primaryLanguage": null,
      "pushedAt": "2020-05-09T06:50:37Z",
      "stargazersCount": 0,
      "topics": [],
      "updatedAt": "2021-11-19T18:53:11Z"
    }
  ],
  "schemaVersion": 3,
  "source": {
    "provider": "github-graphql",
    "status": "ok",
    "username": "haarsh01"
  }
}
